setup.py
bh107/__init__.py
bh107/_dtype_util.py
bh107/array_create.py
bh107/bharray.py
bh107/random.py
bh107/reorganization.py
bh107/summations.py
bh107/ufuncs.py
bh107/user_kernel.py
bh107/util.py
bh107/version.py
bh107.egg-info/PKG-INFO
bh107.egg-info/SOURCES.txt
bh107.egg-info/dependency_links.txt
bh107.egg-info/requires.txt
bh107.egg-info/top_level.txt