Metadata-Version: 1.2
Name: bh107
Version: 0.11.0.post60
Summary: Bohrium for Python <www.bh107.org>
Home-page: http://bh107.org
Author: The Bohrium Team
Author-email: contact@bh107.org
Maintainer: Mads R. B. Kristensen
Maintainer-email: madsbk@gmail.com
License: GPL
Keywords: Bohrium,bh107,pyopencl,pycuda
Platform: Linux
Platform: OSX
Classifier: Development Status :: 4 - Beta
Classifier: Intended Audience :: End Users/Desktop
Classifier: Topic :: Multimedia
Classifier: License :: OSI Approved :: GNU General Public License (GPL)
Classifier: Programming Language :: Python :: 2.7
Classifier: Programming Language :: Python :: 3
